smlmvis/__init__.py
smlmvis/__main__.py
smlmvis/_version.py
smlmvis/abbelightreader.py
smlmvis/dlpreader.py
smlmvis/ellipsoidwriter.py
smlmvis/epflreader.py
smlmvis/gsdreader.py
smlmvis/rainstormreader.py
smlmvis/thunderstormreader.py
smlmvis/tools.py
smlmvis/vtuwriter.py
smlmvis-0.1.0.dist-info/LICENSE
smlmvis-0.1.0.dist-info/METADATA
smlmvis-0.1.0.dist-info/WHEEL
smlmvis-0.1.0.dist-info/top_level.txt
smlmvis-0.1.0.dist-info/RECORD
